{"format":1,"version":"4.4.1","settings":"de6d4dcbfe6a1e0bf94a15c4c5f957e7","files":{"project___init___py":{"hash":"837026b841be2cea48cb506e1c09340b","index":{"nums":[1,19,0,10,0,0,0],"html_filename":"project___init___py.html","relative_filename":"project/__init__.py"}},"project_api_models_py":{"hash":"dfd33b85b28f7ee29f8040f327fb3720","index":{"nums":[1,30,0,20,2,0,2],"html_filename":"project_api_models_py.html","relative_filename":"project/api/models.py"}},"project_api_users_py":{"hash":"0db5907aaa44f0878a57bb50d57dd265","index":{"nums":[1,55,0,2,12,1,1],"html_filename":"project_api_users_py.html","relative_filename":"project/api/users.py"}},"project_config_py":{"hash":"cbe351807609d76538602bd8aea1a84e","index":{"nums":[1,23,0,0,0,0,0],"html_filename":"project_config_py.html","relative_filename":"project/config.py"}}}}